retry.py
avilabsutils_retry-0.0.1.dist-info/METADATA
avilabsutils_retry-0.0.1.dist-info/WHEEL
avilabsutils_retry-0.0.1.dist-info/top_level.txt
avilabsutils_retry-0.0.1.dist-info/RECORD
