Metadata-Version: 2.1
Name: avilabsutils-retry
Version: 0.0.1
Summary: Retry decorator for automatically retrying functions
Home-page: https://github.com/avilay/utils/retry
Author: Avilay Parekh
Author-email: avilay@gmail.com
License: UNKNOWN
Platform: UNKNOWN
Classifier: Programming Language :: Python :: 3
Classifier: License :: OSI Approved :: MIT License
Classifier: Operating System :: OS Independent
Requires-Python: >=3.6
